masterpiece_plugin/__init__.py
masterpiece_plugin/hello_world.py
masterpiece_plugin/py.typed
masterpiece_plugin-0.1.10.dist-info/licenses/LICENSE.rst
masterpiece_plugin-0.1.10.dist-info/METADATA
masterpiece_plugin-0.1.10.dist-info/WHEEL
masterpiece_plugin-0.1.10.dist-info/entry_points.txt
masterpiece_plugin-0.1.10.dist-info/top_level.txt
masterpiece_plugin-0.1.10.dist-info/RECORD
